toever
