Metadata-Version: 1.0
Name: toever
Version: 1.9.5
Summary: Evernote command line tool
Home-page: https://github.com/ngc224/toever
Author: Yoshihiko Nishida
Author-email: nishida@ngc224.org
License: UNKNOWN
Platform: UNKNOWN
